sysmon_sdk/__init__.py
sysmon_sdk/cli.py
sysmon_sdk/config.py
sysmon_sdk/core.py
sysmon_sdk/daemon.py
sysmon_sdk-0.1.4.dist-info/METADATA
sysmon_sdk-0.1.4.dist-info/WHEEL
sysmon_sdk-0.1.4.dist-info/entry_points.txt
sysmon_sdk-0.1.4.dist-info/top_level.txt
sysmon_sdk-0.1.4.dist-info/RECORD
