Metadata-Version: 2.4
Name: sysmon-sdk
Version: 0.1.4
Summary: Python SDK and CLI to interact with the sysmon daemon
Author-email: Arun Gupta <arun_o_gupta@gmail.com>
License: MIT
Requires-Python: >=3.8
Requires-Dist: psutil
Requires-Dist: pytest
Requires-Dist: pytest-cov
Requires-Dist: pytest-order
